joshuaavalon/favicon/__init__.py
joshuaavalon/favicon/__main__.py
joshuaavalon_favicon-1.0.0.dist-info/LICENSE
joshuaavalon_favicon-1.0.0.dist-info/METADATA
joshuaavalon_favicon-1.0.0.dist-info/WHEEL
joshuaavalon_favicon-1.0.0.dist-info/top_level.txt
joshuaavalon_favicon-1.0.0.dist-info/RECORD
