Metadata-Version: 2.1
Name: joshuaavalon-favicon
Version: 1.0.0
Summary: Download favicon from urls
Home-page: https://github.com/joshuaavalon/favicon
Author: Joshua Avalon
License: UNKNOWN
Platform: UNKNOWN
Classifier: Programming Language :: Python :: 3
Classifier: Programming Language :: Python :: 3 :: Only
Classifier: Programming Language :: Python :: 3.7
Classifier: License :: OSI Approved :: Apache Software License
Classifier: Operating System :: OS Independent
Requires-Python: >=3.7
Requires-Dist: Pillow (>=5.3.0)
Requires-Dist: beautifulsoup4 (>=4.6.3)
Requires-Dist: requests (>=2.21.0)
